{
  "species_slug": "mentha_villosa",
  "scientific_name": "Mentha x villosa Huds.",
  "common_names": [
    "Hierbabuena criolla"
  ],
  "family": "Lamiaceae",
  "category": "medicinales_alelopaticas",
  "cultivable": true,
  "conservation_status": "cultivo_comun",
  "thermal_zones": [
    "calido",
    "templado",
    "frio"
  ],
  "roles_in_guild": [
    "crop",
    "pest_repellent",
    "ground_cover"
  ],
  "antagonists": [],
  "especies_nativas_sustitutas": [],
  "propagation": {
    "metodo_principal": "estolon",
    "notas": "Hibrido esteril propagado exclusivamente por estolones. Ampliamente cultivada en huertas caseras colombianas para infusiones medicinales y agua de panela con hierbabuena."
  },
  "requirements": {
    "agua": "alto",
    "altitud_msnm": {
      "min_absoluto": 300,
      "optimo_min": 800,
      "optimo_max": 2500,
      "max_absoluto": 3000
    },
    "temperatura_c": {
      "helada_letal": -5,
      "optimo_min": 12,
      "optimo_max": 24,
      "max_tolerable": 30
    },
    "radiacion": "sombra_parcial",
    "drenaje_requerido": "medio"
  },
  "valor_pedagogico": "La hierbabuena criolla o menta vellosa (Mentha × villosa Huds., Lamiaceae), llamada también menta de Castilla, es un híbrido natural entre Mentha spicata y Mentha suaveolens originario de Europa y ampliamente naturalizado en huertas caseras colombianas desde zonas cálidas húmedas hasta el altiplano frío (300-2.500 msnm: Llanos, Eje cafetero, Cundinamarca, Boyacá, Nariño, Antioquia). Tolera heladas suaves hasta -5 °C y rebrota desde el rizoma cuando el frío quema la parte aérea. Es una lección viva de hibridación interespecífica y propagación vegetativa que enseña a niñas y niños un concepto biológico clave: por ser un híbrido estéril (sus semillas casi nunca germinan o producen plantas inviables) solo se reproduce por estolones — tallos rastreros que se entierran y echan raíces en cada nudo — lo que significa que todas las matas de hierbabuena del país son clones genéticos, copias idénticas de una misma planta madre que se ha multiplicado por miles de manos campesinas durante siglos. Esta propagación vegetativa preserva exactamente el aroma, el sabor y el contenido de aceite esencial (mentol, mentona, pulegona) generación tras generación, garantizando que el agua de panela con hierbabuena de la abuela sepa igual que la del nieto. Manejo agroecológico: siembra de estolones en suelo húmedo y rico en materia orgánica, sombra parcial preferida en clima cálido, riego frecuente, cosecha de hojas y tallos tiernos antes de floración para máxima concentración de aceites esenciales, control del crecimiento con bordes enterrados porque tiende a invadir camas vecinas. Usos: aromática digestiva, carminativa, antiespasmódica, repelente suave de hormigas en despensa. Fuentes Tier A: POWO Kew, GBIF Backbone Taxonomy, Pérez Arbeláez 1947 Plantas Útiles, JBB Plantas Medicinales Cundinamarca-Boyacá, Pamplona-Roger 2006.",
  "sources": [
    {
      "id": "perez-arbelaez-1947-plantas-utiles",
      "title": "perez-arbelaez-1947-plantas-utiles",
      "tier": "A",
      "url": null
    },
    {
      "id": "gbif-taxonomic-backbone",
      "title": "gbif-taxonomic-backbone",
      "tier": "A",
      "url": "https://www.gbif.org/dataset/d7dddbf4-2cf0-4f39-9b2a-bb099caae36c"
    },
    {
      "id": "powo-kew",
      "title": "powo-kew",
      "tier": "A",
      "url": "https://powo.science.kew.org"
    },
    {
      "id": "jbb-plantas-medicinales",
      "title": "jbb-plantas-medicinales",
      "tier": "A",
      "url": null
    },
    {
      "id": "pamplona-roger-2006-plantas-medicinales",
      "title": "pamplona-roger-2006-plantas-medicinales",
      "tier": "B",
      "url": null
    }
  ],
  "_generated_by": "scripts/build-cycle-content-from-catalog.mjs",
  "_generated_at": "2026-05-19T00:42:57.379Z"
}
