{
  "species_slug": "rubus_glaucus_sin_espinas",
  "scientific_name": "Rubus glaucus Benth. 'Sin Espinas'",
  "common_names": [
    "Mora andina sin espinas"
  ],
  "family": "Rosaceae",
  "category": "frutales_perennes",
  "cultivable": true,
  "conservation_status": "cultivo_comun",
  "thermal_zones": [
    "frio",
    "templado"
  ],
  "roles_in_guild": [
    "crop",
    "pollinator_attractor"
  ],
  "antagonists": [],
  "especies_nativas_sustitutas": [],
  "propagation": {
    "metodo_principal": "acodo",
    "notas": "Variedad seleccionada para facilitar la poda y cosecha sin las espinas tradicionales; requiere tutorado en espaldera."
  },
  "requirements": {
    "agua": "medio",
    "altitud_msnm": {
      "min_absoluto": 1500,
      "optimo_min": 1800,
      "optimo_max": 2600,
      "max_absoluto": 2800
    },
    "temperatura_c": {
      "helada_letal": -2,
      "optimo_min": 13,
      "optimo_max": 18,
      "max_tolerable": 22
    },
    "radiacion": "sol_pleno",
    "drenaje_requerido": "bueno"
  },
  "valor_pedagogico": "La mora de Castilla sin espinas (Rubus glaucus Benth. cv. sin espinas, también llamado morera andina) es una rosácea perenne híbrida desarrollada para facilitar la cosecha (sin espinas en cañas), variedad comercial dominante en Colombia. Se cultiva en Cundinamarca (Subachoque, San Bernardo, Silvania), Boyacá, Antioquia, Cauca, Nariño y Valle del Cauca entre 1.800 y 2.800 msnm en zona térmica fría a templada. Ciclo a primera cosecha 8-10 meses; productividad sostenida 5-8 años. Rendimiento 10-15 t/ha en sistema agroecológico. Tutorado horizontal con alambre doble o espaldera T. Manejo: poda anual cañas viejas, mulch grueso (paja, virutas), fertilización con compost + biol, control de antracnosis (Colletotrichum gloeosporioides) con caldo bordelés. Fuentes Tier A: AGROSAVIA, ICA Resolución 3168/2015, POWO Kew, GBIF Backbone Taxonomy.",
  "sources": [
    {
      "id": "nrc-1989-cultivos-andinos",
      "title": "nrc-1989-cultivos-andinos",
      "tier": "A",
      "url": null
    },
    {
      "id": "agrosavia-leguminosas-andinas",
      "title": "agrosavia-leguminosas-andinas",
      "tier": "A",
      "url": null
    },
    {
      "id": "gbif-taxonomic-backbone",
      "title": "gbif-taxonomic-backbone",
      "tier": "A",
      "url": "https://www.gbif.org/dataset/d7dddbf4-2cf0-4f39-9b2a-bb099caae36c"
    },
    {
      "id": "ica-resolucion-3168-2015",
      "title": "ica-resolucion-3168-2015",
      "tier": "A",
      "url": null
    }
  ],
  "_generated_by": "scripts/build-cycle-content-from-catalog.mjs",
  "_generated_at": "2026-05-19T00:42:57.365Z"
}
